ncs2mef/__init__.py
ncs2mef/ncs_reader.py
ncs2mef/test/__init__.py
ncs2mef/test/test_ncs_reader.py
ncs2mef-0.0.1.dist-info/LICENSE
ncs2mef-0.0.1.dist-info/METADATA
ncs2mef-0.0.1.dist-info/WHEEL
ncs2mef-0.0.1.dist-info/top_level.txt
ncs2mef-0.0.1.dist-info/RECORD
