Metadata-Version: 2.1
Name: ncs2mef
Version: 0.0.1
Summary: Custom made Python reader for Neuralynx Cheetah NCS files.
Home-page: https://github.com/mselair/ncs2mef
Author: Filip Mivalt
Author-email: mivalt.filip@mayo.edu
License: UNKNOWN
Platform: UNKNOWN
Classifier: Development Status :: 3 - Alpha
Classifier: Intended Audience :: Healthcare Industry
Classifier: Intended Audience :: Science/Research
Classifier: License :: OSI Approved :: Apache Software License
Classifier: Programming Language :: Python :: 3.6
Classifier: Operating System :: POSIX :: Linux
Classifier: Topic :: Scientific/Engineering :: Medical Science Apps.
Requires-Python: >=3.6
Requires-Dist: numpy
